tuir/__init__.py
tuir/__main__.py
tuir/__version__.py
tuir/clipboard.py
tuir/config.py
tuir/content.py
tuir/docs.py
tuir/exceptions.py
tuir/inbox_page.py
tuir/mime_parsers.py
tuir/oauth.py
tuir/objects.py
tuir/page.py
tuir/submission_page.py
tuir/subreddit_page.py
tuir/subscription_page.py
tuir/terminal.py
tuir/theme.py
tuir/packages/__init__.py
tuir/packages/mailcap/__init__.py
tuir/packages/mailcap/mailcap.py
tuir/packages/mailcap/test_mailcap.py
tuir/packages/praw/__init__.py
tuir/packages/praw/decorator_helpers.py
tuir/packages/praw/decorators.py
tuir/packages/praw/errors.py
tuir/packages/praw/handlers.py
tuir/packages/praw/helpers.py
tuir/packages/praw/internal.py
tuir/packages/praw/multiprocess.py
tuir/packages/praw/objects.py
tuir/packages/praw/praw.ini
tuir/packages/praw/settings.py
tuir/templates/index.html
tuir/templates/mailcap
tuir/templates/tuir.cfg
tuir/themes/colorblind-dark.cfg
tuir/themes/default.cfg.example
tuir/themes/gruvbox.cfg
tuir/themes/molokai.cfg
tuir/themes/papercolor.cfg
tuir/themes/solarized-dark.cfg
tuir/themes/solarized-light.cfg
tuir_continued-1.32.0.data/data/share/man/man1/tuir.1
tuir_continued-1.32.0.dist-info/licenses/AUTHORS.rst
tuir_continued-1.32.0.dist-info/licenses/COPYING
tuir_continued-1.32.0.dist-info/licenses/LICENSE.MIT
tuir_continued-1.32.0.dist-info/METADATA
tuir_continued-1.32.0.dist-info/WHEEL
tuir_continued-1.32.0.dist-info/entry_points.txt
tuir_continued-1.32.0.dist-info/top_level.txt
tuir_continued-1.32.0.dist-info/RECORD
