Metadata-Version: 2.4
Name: tuir-continued
Version: 1.32.0
Summary: A simple terminal viewer for Reddit (Terminal UI for Reddit)
Home-page: https://gitlab.com/Chocimier/tuir
Author: Chocimier
Author-email: chocimier@tlen.pl
License: GPL-3.0-only
Keywords: reddit terminal praw curses
Classifier: Intended Audience :: End Users/Desktop
Classifier: Environment :: Console :: Curses
Classifier: Operating System :: MacOS :: MacOS X
Classifier: Operating System :: POSIX
Classifier: Natural Language :: English
Classifier: License :: OSI Approved :: GNU General Public License v3 (GPLv3)
Classifier: Programming Language :: Python :: 2.7
Classifier: Programming Language :: Python :: 3.9
Classifier: Programming Language :: Python :: 3.10
Classifier: Programming Language :: Python :: 3.11
Classifier: Programming Language :: Python :: 3.12
Classifier: Programming Language :: Python :: 3.13
Classifier: Programming Language :: Python :: 3.14
Classifier: Topic :: Terminals
Classifier: Topic :: Internet :: WWW/HTTP :: Dynamic Content :: Message Boards
Classifier: Topic :: Internet :: WWW/HTTP :: Dynamic Content :: News/Diary
License-File: LICENSE.MIT
License-File: COPYING
License-File: AUTHORS.rst
Requires-Dist: beautifulsoup4
Requires-Dist: decorator
Requires-Dist: kitchen
Requires-Dist: requests>=2.4.0
Requires-Dist: six
Provides-Extra: test
Requires-Dist: coveralls; extra == "test"
Requires-Dist: pytest>=3.1.0; extra == "test"
Requires-Dist: coverage; extra == "test"
Requires-Dist: mock; extra == "test"
Requires-Dist: pylint; extra == "test"
Requires-Dist: vcrpy; extra == "test"
Requires-Dist: mailcap-fix; python_version < "3.6"
Dynamic: author
Dynamic: author-email
Dynamic: classifier
Dynamic: description
Dynamic: description-content-type
Dynamic: home-page
Dynamic: keywords
Dynamic: license
Dynamic: license-file
Dynamic: provides-extra
Dynamic: requires-dist
Dynamic: summary
